{
  "companies": [
    {
      "id": 1,
      "logo": "http://example.com/logo1.png",
      "name": "Tech Corp",
      "status": "Active"
    },
    {
      "id": 2,
      "logo": "http://example.com/logo2.png",
      "name": "Media Group",
      "status": "Inactive"
    },
    {
      "id": 3,
      "logo": "https://example.com/logo.png",
      "name": "Update Example Company",
      "status": "Active",
      "createdAt": "2025-01-18T09:52:18.981Z"
    }
  ],
  "users": [
    {
      "id": 1,
      "firstname": "John",
      "lastname": "Meyer",
      "username": "admin",
      "password": "$2b$10$9SwdHjs.pQq7AxYh1aCNieGCCBb837O6PNo2G8lMnuXeONjj/4W0C",
      "type": "Writer",
      "status": "Active"
    },
    {
      "id": 2,
      "firstname": "Richard",
      "lastname": "Alcaide",
      "username": "admin11",
      "password": "$2b$10$XxOccKu2ocdZvLcJhODLLeg8UFPIkkBxx9HcenDl2/kWevV6o7j12",
      "type": "Editor",
      "status": "Active"
    }
  ],
  "articles": [
    {
      "id": 1,
      "image": "http://example.com/image1.jpg",
      "title": "Tech Trends 2025",
      "link": "http://example.com/article1",
      "date": "2025-01-01",
      "content": "Future technology trends in 2025...",
      "status": "Published",
      "writer": 1,
      "editor": 2,
      "company": 1
    },
    {
      "id": 2,
      "image": "http://example.com/image2.jpg",
      "title": "New Media Innovations",
      "link": "http://example.com/article2",
      "date": "2025-02-01",
      "content": "Innovations in the media industry...",
      "status": "For Edit",
      "writer": 1,
      "editor": 2,
      "company": 2
    },
    {
      "id": 3,
      "image": "https://res.cloudinary.com/yogeek-cloudinary/image/upload/v1737339652/samples/iyh0dmaswmujqabbku5n.jpg",
      "title": "Sample Article 1",
      "link": "http://localhost:3000/article/fdsgsg-sgsdg",
      "date": "2025-01-20",
      "content": "Sample Content 1",
      "status": "For Edit",
      "writer": 1,
      "editor": null,
      "company": 2
    },
    {
      "id": 4,
      "image": "https://res.cloudinary.com/yogeek-cloudinary/image/upload/v1737342371/samples/bbdvhqmw8whhod6lxye1.jpg",
      "title": "Testing",
      "link": "http://localhost:3000/article/aasgaga",
      "date": "2025-01-20",
      "content": "asgasgasgag",
      "status": "For Edit",
      "writer": 1,
      "editor": null,
      "company": 3
    }
  ]
}